liquidcosmo/__init__.py
liquidcosmo/chain.py
liquidcosmo/folder.py
liquidcosmo/foldercollection.py
liquidcosmo/settings.py
liquidcosmo/util.py
liquidcosmo-0.3.4.dist-info/METADATA
liquidcosmo-0.3.4.dist-info/WHEEL
liquidcosmo-0.3.4.dist-info/top_level.txt
liquidcosmo-0.3.4.dist-info/RECORD
