Metadata-Version: 2.4
Name: liquidcosmo
Version: 0.3.4
Summary: Cosmological analyses made easy
Home-page: https://github.com/schoeneberg/liquidcosmo/
Author: Nils Schöneberg
Classifier: Programming Language :: Python :: 3.8
Classifier: License :: OSI Approved :: GNU General Public License v3 (GPLv3)
Dynamic: author
Dynamic: classifier
Dynamic: description
Dynamic: description-content-type
Dynamic: home-page
Dynamic: summary
